{
  "cities": [
    {
      "cityName": "Lisbon",
      "country": "Portugal",
      "emoji": "🇵🇹",
      "date": "2027-10-31T15:59:59.138Z",
      "notes": "My favorite city so far!",
      "position": {
        "lat": 38.727881642324164,
        "lng": -9.140900099907554
      },
      "id": 73930385
    },
    {
      "cityName": "Madrid",
      "country": "Spain",
      "emoji": "🇪🇸",
      "date": "2027-07-15T08:22:53.976Z",
      "notes": "",
      "position": {
        "lat": 40.46635901755316,
        "lng": -3.7133789062500004
      },
      "id": 17806751
    },
    {
      "cityName": "Berlin",
      "country": "Germany",
      "emoji": "🇩🇪",
      "date": "2027-02-12T09:24:11.863Z",
      "notes": "Amazing 😃",
      "position": {
        "lat": 52.53586782505711,
        "lng": 13.376933665713324
      },
      "id": 98443197
    },
    {
      "cityName": "Nijar",
      "country": "Spain",
      "emoji": "🇪🇸",
      "date": "2023-04-03T07:47:59.202Z",
      "notes": "",
      "position": {
        "lat": "36.967508314568164",
        "lng": "-2.13128394200588"
      },
      "id": 98443198
    },
    {
      "id": "a130",
      "cityName": "Aguaton",
      "country": "Spain",
      "emoji": "🇪🇸",
      "date": "2024-09-27T13:28:53.397Z",
      "notes": "dfghjk",
      "position": {
        "lat": "40.6306300839918",
        "lng": "-1.2084960937500002"
      }
    },
    {
      "id": "288b",
      "cityName": "Galindo y Perahuy",
      "country": "Spain",
      "emoji": "🇪🇸",
      "date": "2024-09-28T11:40:36.940Z",
      "notes": "notes for today",
      "position": {
        "lat": "40.94808308911551",
        "lng": "-5.888671875"
      }
    },
    {
      "id": "318a",
      "cityName": "Piaski",
      "country": "Poland",
      "emoji": "🇵🇱",
      "date": "2024-09-28T11:40:52.592Z",
      "notes": "dfghj",
      "position": {
        "lat": "51.86464318601257",
        "lng": "17.182617187500004"
      }
    }
  ]
}